mypythonpackage12345/__init__.py
mypythonpackage12345/task7.py
mypythonpackage12345/tasks1-4.py
mypythonpackage12345/tasks5-6.py
mypythonpackage12345/tasks8-9.py
mypythonpackage12345-1.0.0.dist-info/METADATA
mypythonpackage12345-1.0.0.dist-info/WHEEL
mypythonpackage12345-1.0.0.dist-info/top_level.txt
mypythonpackage12345-1.0.0.dist-info/RECORD
